tb_vendor/__init__.py
tb_vendor/exceptions.py
tb_vendor/logger_config.py
tb_vendor/models.py
tb_vendor/tb_utils.py
tb_vendor/utils.py
tb_vendor/mqtt/__init__.py
tb_vendor/mqtt/callbacks.py
tb_vendor/mqtt/clients.py
tb_vendor/mqtt/parsers.py
tb_vendor/mqtt/processes.py
tb_vendor/mqtt/threads.py
tb_vendor/mqtt/topics.py
tb_vendor/rest/__init__.py
tb_vendor/rest/devices.py
tb_vendor/rest/login.py
tb_vendor/rest/models.py
tb_vendor/telemetry/__init__.py
tb_vendor/telemetry/telemetry.py
tb_vendor-0.12.0.dist-info/LICENSE
tb_vendor-0.12.0.dist-info/METADATA
tb_vendor-0.12.0.dist-info/WHEEL
tb_vendor-0.12.0.dist-info/top_level.txt
tb_vendor-0.12.0.dist-info/RECORD
